viasckde/__init__.py
viasckde/_utils.py
viasckde/viasckde.py
viasckde-1.0.1.dist-info/METADATA
viasckde-1.0.1.dist-info/WHEEL
viasckde-1.0.1.dist-info/top_level.txt
viasckde-1.0.1.dist-info/RECORD
