Metadata-Version: 2.4
Name: viasckde
Version: 1.0.1
Summary: VIASCKDE: internal cluster validity index (KDE-weighted compactness & separation)
Author-email: Ali Şenol <alisenol@tarsus.edu.tr>
License: MIT
Project-URL: Documentation, https://github.com/senolali/viasckde
Project-URL: Homepage, https://github.com/senolali/viasckde
Project-URL: Paper, https://doi.org/10.1155/2022/4059302
Project-URL: Issues, https://github.com/senolali/viasckde
Classifier: Programming Language :: Python :: 3
Classifier: License :: OSI Approved :: MIT License
Classifier: Operating System :: OS Independent
Classifier: Intended Audience :: Science/Research
Classifier: Topic :: Scientific/Engineering :: Artificial Intelligence
Requires-Python: >=3.8
Requires-Dist: numpy>=1.21
Requires-Dist: scikit-learn>=1.0
Requires-Dist: scipy>=1.7
